lightestlib-0.1.dist-info/licenses/LICENSE
testlib/__init__.py
testlib/base/__init__.py
testlib/base/testcase.py
testlib/base/testcasevar.py
testlib/base/testmessage.py
testlib/base/testmessageformatter.py
testlib/base/testoutputer.py
testlib/base/testsuite.py
testlib/casetypes/__init__.py
testlib/casetypes/testcases/__init__.py
testlib/casetypes/testcases/plain.py
testlib/casetypes/testcasevars/__init__.py
testlib/casetypes/testcasevars/exception.py
testlib/casetypes/testcasevars/output.py
testlib/casetypes/testcasevars/result.py
testlib/formatters/__init__.py
testlib/formatters/logformatter.py
testlib/formatters/stdformatter.py
testlib/outputers/__init__.py
testlib/outputers/fileoutputer.py
testlib/outputers/outputers_generater.py
testlib/outputers/stdoutputer.py
testlib/suites/__init__.py
testlib/suites/assertsuit.py
testlib/suites/plainsuite.py
testlib/utils/__init__.py
testlib/utils/memory_monitor.py
testlib/utils/runner.py
testlib/utils/timer.py
lightestlib-0.1.dist-info/METADATA
lightestlib-0.1.dist-info/WHEEL
lightestlib-0.1.dist-info/top_level.txt
lightestlib-0.1.dist-info/RECORD
