Metadata-Version: 2.4
Name: lightestlib
Version: 0.1
Summary: A simple, pythonic Python test framework
Author-email: Alwaylone <221159233+Alwaylone9801@users.noreply.github.com>
License: MIT License
Project-URL: Homepage, https://github.com/Alwaylone9801/testlib
Project-URL: Repository, https://github.com/Alwaylone9801/testlib
Classifier: Development Status :: 3 - Alpha
Classifier: Intended Audience :: Developers
Classifier: Intended Audience :: Education
Classifier: License :: OSI Approved :: MIT License
Classifier: Operating System :: OS Independent
Classifier: Programming Language :: Python :: 3
Classifier: Programming Language :: Python :: 3.10
Classifier: Programming Language :: Python :: 3.11
Classifier: Topic :: Software Development :: Testing
Requires-Python: >=3.10
License-File: LICENSE
Dynamic: license-file
